omicsdata/__init__.py
omicsdata/cn/estimate.py
omicsdata/csv/parse.py
omicsdata/npz/__init__.py
omicsdata/npz/archive.py
omicsdata/ssm/__init__.py
omicsdata/ssm/columns.py
omicsdata/ssm/common.py
omicsdata/ssm/constants.py
omicsdata/ssm/parse.py
omicsdata/ssm/supervariants.py
omicsdata/ssm/convert/ssm_base_converter.py
omicsdata/ssm/convert/ssm_to_fastclone.py
omicsdata/ssm/convert/ssm_to_mobster_tsv.py
omicsdata/ssm/convert/ssm_to_pcvi_tsv.py
omicsdata/ssm/convert/ssm_to_scc_tsv.py
omicsdata/ssm/convert/ssm_to_viber.py
omicsdata/ssm/convert/vcf_to_ssm.py
omicsdata/tree/__init__.py
omicsdata/tree/adj.py
omicsdata/tree/newick.py
omicsdata/tree/parents.py
omicsadata-1.99.dist-info/LICENSE
omicsadata-1.99.dist-info/METADATA
omicsadata-1.99.dist-info/WHEEL
omicsadata-1.99.dist-info/top_level.txt
omicsadata-1.99.dist-info/RECORD
